json_doc/__init__.py
json_doc/json_doc.py
tests/__init__.py
tests/test_json_doc.py
json_doc-0.1.3.dist-info/LICENSE
json_doc-0.1.3.dist-info/METADATA
json_doc-0.1.3.dist-info/WHEEL
json_doc-0.1.3.dist-info/top_level.txt
json_doc-0.1.3.dist-info/RECORD
