Metadata-Version: 2.1
Name: json-doc
Version: 0.1.3
Summary: Utility Functions for JSON Document
Home-page: http://github.com/ddfs/json-doc
Author: Fatih Piristine
Author-email: fatihpiristine@gmail.com
License: Apache Software License
Keywords: json,document,pointer
Platform: any
Classifier: Programming Language :: Python
Classifier: License :: OSI Approved :: Apache Software License
Classifier: Operating System :: OS Independent
Classifier: Topic :: Software Development :: Libraries :: Python Modules
Classifier: Topic :: Utilities
